pysimrel/__init__.py
pysimrel/pysimrel.py
pysimrel/simrelplot.py
pysimrel/utilities.py
pysimrel/version.py
tests/__init__.py
tests/test_get_cov.py
tests/test_get_eigen.py
tests/test_get_relpred.py
tests/test_get_rotate.py
tests/test_get_rotation.py
tests/test_parse_param.py
tests/test_plot_true_coef.py
tests/test_sample_extra_pos.py
pysimrel-0.6.1.dist-info/METADATA
pysimrel-0.6.1.dist-info/WHEEL
pysimrel-0.6.1.dist-info/top_level.txt
pysimrel-0.6.1.dist-info/RECORD
