Metadata-Version: 2.1
Name: pysimrel
Version: 0.6.1
Summary: Simulation of Linear Model Data
Home-page: https://github.com/simulatr/pysimrel
Author: Raju Rimal
Author-email: therimalaya@gmail.com
Classifier: Programming Language :: Python :: 3
Classifier: License :: OSI Approved :: MIT License
Classifier: Operating System :: OS Independent
Requires-Python: >=3.6
